LICENSE
MANIFEST.in
README.md
README.rst
setup.py
django_swapfield.egg-info/PKG-INFO
django_swapfield.egg-info/SOURCES.txt
django_swapfield.egg-info/dependency_links.txt
django_swapfield.egg-info/top_level.txt
swapfield/__init__.py
swapfield/apps.py
swapfield/fields.py
tests/__init__.py
tests/test_integer.py
tests/testapp/__init__.py
tests/testapp/models.py
tests/testapp/migrations/0001_initial.py
tests/testapp/migrations/__init__.py
tests/testproject/__init__.py
tests/testproject/manage.py
tests/testproject/settings.py
tests/testproject/urls.py