Metadata-Version: 1.1
Name: django-swapfield
Version: 0.1.0
Summary: Django field with automatic values swap
Home-page: https://github.com/SRJ9/django-swapfield.git
Author: Jose ER
Author-email: srj9es@gmail.com
License: MIT
Download-URL: https://github.com/SRJ9/django-swapfield/archive/master.zip
Keywords: Django,field,integer,swap
Platform: UNKNOWN
Classifier: Development Status :: 4 - Beta
Classifier: Framework :: Django
Classifier: Framework :: Django :: 1.8
Classifier: Framework :: Django :: 1.9
Classifier: Framework :: Django :: 1.10
Classifier: Intended Audience :: Developers
Classifier: Intended Audience :: End Users/Desktop
Classifier: License :: OSI Approved :: MIT License
Classifier: Programming Language :: Python :: 2.7
Classifier: Programming Language :: Python :: 3.3
Classifier: Programming Language :: Python :: 3.4
Classifier: Programming Language :: Python :: 3.5
